BitConvertAccesslib/__init__.py
BitConvertAccesslib/data_manager.py
BitConvertAccesslib/deep_data_manager.py
DDBitConvertAccesslib-0.1.0.dist-info/METADATA
DDBitConvertAccesslib-0.1.0.dist-info/WHEEL
DDBitConvertAccesslib-0.1.0.dist-info/top_level.txt
DDBitConvertAccesslib-0.1.0.dist-info/RECORD
